pywFM/__init__.py
pywFM/libfm/bin/convert
pywFM/libfm/bin/libFM
pywFM/libfm/bin/transpose
pywFM-0.12.3.dist-info/DESCRIPTION.rst
pywFM-0.12.3.dist-info/METADATA
pywFM-0.12.3.dist-info/RECORD
pywFM-0.12.3.dist-info/WHEEL
pywFM-0.12.3.dist-info/metadata.json
pywFM-0.12.3.dist-info/top_level.txt
