Metadata-Version: 2.0
Name: pywFM
Version: 0.12.3
Summary: Python wrapper for libFM
Home-page: http://github.com/jfloff/pywFM
Author: Joao Loff
Author-email: jfloff@gmail.com
License: MIT
Keywords: python wrapper libfm factorization machines
Platform: UNKNOWN
Classifier: Development Status :: 3 - Alpha
Classifier: License :: OSI Approved :: MIT License
Classifier: Programming Language :: Python :: 2.7
Classifier: Topic :: Scientific/Engineering :: Information Analysis
Requires-Dist: numpy
Requires-Dist: scipy
Requires-Dist: scikit-learn
Requires-Dist: pandas
